{"protocol":{"minReaderVersion":1,"minWriterVersion":1}}
{"metaData":{"id":"77ef27d6-ea9a-4904-8175-3006e4388c8e","name":null,"description":null,"format":{"provider":"parquet","options":{}},"schemaString":"{\"type\":\"struct\",\"fields\":[{\"name\":\"CustomerID\",\"type\":\"long\",\"nullable\":true,\"metadata\":{}},{\"name\":\"CustomerName\",\"type\":\"string\",\"nullable\":true,\"metadata\":{}},{\"name\":\"BillToCustomerID\",\"type\":\"long\",\"nullable\":true,\"metadata\":{}},{\"name\":\"CustomerCategoryID\",\"type\":\"long\",\"nullable\":true,\"metadata\":{}},{\"name\":\"BuyingGroupID\",\"type\":\"double\",\"nullable\":true,\"metadata\":{}},{\"name\":\"PrimaryContactPersonID\",\"type\":\"long\",\"nullable\":true,\"metadata\":{}},{\"name\":\"AlternateContactPersonID\",\"type\":\"double\",\"nullable\":true,\"metadata\":{}},{\"name\":\"DeliveryMethodID\",\"type\":\"long\",\"nullable\":true,\"metadata\":{}},{\"name\":\"DeliveryCityID\",\"type\":\"long\",\"nullable\":true,\"metadata\":{}},{\"name\":\"PostalCityID\",\"type\":\"long\",\"nullable\":true,\"metadata\":{}},{\"name\":\"CreditLimit\",\"type\":\"double\",\"nullable\":true,\"metadata\":{}},{\"name\":\"AccountOpenedDate\",\"type\":\"timestamp\",\"nullable\":true,\"metadata\":{}},{\"name\":\"StandardDiscountPercentage\",\"type\":\"long\",\"nullable\":true,\"metadata\":{}},{\"name\":\"IsStatementSent\",\"type\":\"boolean\",\"nullable\":true,\"metadata\":{}},{\"name\":\"IsOnCreditHold\",\"type\":\"boolean\",\"nullable\":true,\"metadata\":{}},{\"name\":\"PaymentDays\",\"type\":\"long\",\"nullable\":true,\"metadata\":{}},{\"name\":\"PhoneNumber\",\"type\":\"string\",\"nullable\":true,\"metadata\":{}},{\"name\":\"FaxNumber\",\"type\":\"string\",\"nullable\":true,\"metadata\":{}},{\"name\":\"DeliveryRun\",\"type\":\"double\",\"nullable\":true,\"metadata\":{}},{\"name\":\"RunPosition\",\"type\":\"double\",\"nullable\":true,\"metadata\":{}},{\"name\":\"WebsiteURL\",\"type\":\"string\",\"nullable\":true,\"metadata\":{}},{\"name\":\"DeliveryAddressLine1\",\"type\":\"string\",\"nullable\":true,\"metadata\":{}},{\"name\":\"DeliveryAddressLine2\",\"type\":\"string\",\"nullable\":true,\"metadata\":{}},{\"name\":\"DeliveryPostalCode\",\"type\":\"long\",\"nullable\":true,\"metadata\":{}},{\"name\":\"DeliveryLocation\",\"type\":\"string\",\"nullable\":true,\"metadata\":{}},{\"name\":\"PostalAddressLine1\",\"type\":\"string\",\"nullable\":true,\"metadata\":{}},{\"name\":\"PostalAddressLine2\",\"type\":\"string\",\"nullable\":true,\"metadata\":{}},{\"name\":\"PostalPostalCode\",\"type\":\"long\",\"nullable\":true,\"metadata\":{}},{\"name\":\"LastEditedBy\",\"type\":\"long\",\"nullable\":true,\"metadata\":{}},{\"name\":\"ValidFrom\",\"type\":\"timestamp\",\"nullable\":true,\"metadata\":{}},{\"name\":\"ValidTo\",\"type\":\"double\",\"nullable\":true,\"metadata\":{}}]}","partitionColumns":[],"createdTime":1697773210234,"configuration":{}}}
{"add":{"path":"0-a021ff4b-dc2e-4102-8762-493c47373833-0.parquet","size":110313,"partitionValues":{},"modificationTime":1697773210233,"dataChange":true,"stats":"{\"numRecords\": 663, \"minValues\": {\"CustomerID\": 1, \"CustomerName\": \"Aakriti Byrraju\", \"BillToCustomerID\": 1, \"CustomerCategoryID\": 3, \"BuyingGroupID\": 1.0, \"PrimaryContactPersonID\": 1001, \"AlternateContactPersonID\": 1002.0, \"DeliveryMethodID\": 3, \"DeliveryCityID\": 15, \"PostalCityID\": 15, \"CreditLimit\": 1100.0, \"AccountOpenedDate\": \"2013-01-01T00:00:00\", \"StandardDiscountPercentage\": 0, \"IsStatementSent\": false, \"IsOnCreditHold\": false, \"PaymentDays\": 7, \"PhoneNumber\": \"(201) 555-0100\", \"FaxNumber\": \"(201) 555-0101\", \"WebsiteURL\": \"http://www.microsoft.com/\", \"DeliveryAddressLine1\": \"Shop 10\", \"DeliveryAddressLine2\": \"1000 Sykorova Boulevard\", \"DeliveryPostalCode\": 90002, \"DeliveryLocation\": \"0xE6100000010C0000000000604B4091F8CBDDDD6964C0\", \"PostalAddressLine1\": \"PO Box 101\", \"PostalAddressLine2\": \"Abbasiville\", \"PostalPostalCode\": 90002, \"LastEditedBy\": 1, \"ValidFrom\": \"2013-01-01T00:00:00\"}, \"maxValues\": {\"CustomerID\": 1061, \"CustomerName\": \"Yves Belisle\", \"BillToCustomerID\": 1061, \"CustomerCategoryID\": 7, \"BuyingGroupID\": 2.0, \"PrimaryContactPersonID\": 3261, \"AlternateContactPersonID\": 2402.0, \"DeliveryMethodID\": 3, \"DeliveryCityID\": 38184, \"PostalCityID\": 38184, \"CreditLimit\": 4630.5, \"AccountOpenedDate\": \"2016-05-07T00:00:00\", \"StandardDiscountPercentage\": 0, \"IsStatementSent\": false, \"IsOnCreditHold\": false, \"PaymentDays\": 7, \"PhoneNumber\": \"(907) 555-0100\", \"FaxNumber\": \"(907) 555-0101\", \"WebsiteURL\": \"http://www.wingtiptoys.com/Yaak\", \"DeliveryAddressLine1\": \"Unit 95\", \"DeliveryAddressLine2\": \"999 Kasesalu Road\", \"DeliveryPostalCode\": 90800, \"DeliveryLocation\": \"0xE6100000010CFFA8F2E2694545406C2D82B5A02A53C0\", \"PostalAddressLine1\": \"PO Box 9990\", \"PostalAddressLine2\": \"senturkville\", \"PostalPostalCode\": 90800, \"LastEditedBy\": 20, \"ValidFrom\": \"2016-05-07T00:00:00\"}, \"nullCount\": {\"CustomerID\": 0, \"CustomerName\": 0, \"BillToCustomerID\": 0, \"CustomerCategoryID\": 0, \"BuyingGroupID\": 261, \"PrimaryContactPersonID\": 0, \"AlternateContactPersonID\": 261, \"DeliveryMethodID\": 0, \"DeliveryCityID\": 0, \"PostalCityID\": 0, \"CreditLimit\": 402, \"AccountOpenedDate\": 0, \"StandardDiscountPercentage\": 0, \"IsStatementSent\": 0, \"IsOnCreditHold\": 0, \"PaymentDays\": 0, \"PhoneNumber\": 0, \"FaxNumber\": 0, \"DeliveryRun\": 663, \"RunPosition\": 663, \"WebsiteURL\": 0, \"DeliveryAddressLine1\": 0, \"DeliveryAddressLine2\": 0, \"DeliveryPostalCode\": 0, \"DeliveryLocation\": 0, \"PostalAddressLine1\": 0, \"PostalAddressLine2\": 0, \"PostalPostalCode\": 0, \"LastEditedBy\": 0, \"ValidFrom\": 0, \"ValidTo\": 663}}"}}
{"commitInfo":{"timestamp":1697773210234,"operation":"CREATE TABLE","operationParameters":{"location":"file:///content/sample_data/Sales.Customers","mode":"ErrorIfExists","protocol":"{\"minReaderVersion\":1,\"minWriterVersion\":1}","metadata":"{\"configuration\":{},\"created_time\":1697773210234,\"description\":null,\"format\":{\"options\":{},\"provider\":\"parquet\"},\"id\":\"77ef27d6-ea9a-4904-8175-3006e4388c8e\",\"name\":null,\"partition_columns\":[],\"schema\":{\"fields\":[{\"metadata\":{},\"name\":\"CustomerID\",\"nullable\":true,\"type\":\"long\"},{\"metadata\":{},\"name\":\"CustomerName\",\"nullable\":true,\"type\":\"string\"},{\"metadata\":{},\"name\":\"BillToCustomerID\",\"nullable\":true,\"type\":\"long\"},{\"metadata\":{},\"name\":\"CustomerCategoryID\",\"nullable\":true,\"type\":\"long\"},{\"metadata\":{},\"name\":\"BuyingGroupID\",\"nullable\":true,\"type\":\"double\"},{\"metadata\":{},\"name\":\"PrimaryContactPersonID\",\"nullable\":true,\"type\":\"long\"},{\"metadata\":{},\"name\":\"AlternateContactPersonID\",\"nullable\":true,\"type\":\"double\"},{\"metadata\":{},\"name\":\"DeliveryMethodID\",\"nullable\":true,\"type\":\"long\"},{\"metadata\":{},\"name\":\"DeliveryCityID\",\"nullable\":true,\"type\":\"long\"},{\"metadata\":{},\"name\":\"PostalCityID\",\"nullable\":true,\"type\":\"long\"},{\"metadata\":{},\"name\":\"CreditLimit\",\"nullable\":true,\"type\":\"double\"},{\"metadata\":{},\"name\":\"AccountOpenedDate\",\"nullable\":true,\"type\":\"timestamp\"},{\"metadata\":{},\"name\":\"StandardDiscountPercentage\",\"nullable\":true,\"type\":\"long\"},{\"metadata\":{},\"name\":\"IsStatementSent\",\"nullable\":true,\"type\":\"boolean\"},{\"metadata\":{},\"name\":\"IsOnCreditHold\",\"nullable\":true,\"type\":\"boolean\"},{\"metadata\":{},\"name\":\"PaymentDays\",\"nullable\":true,\"type\":\"long\"},{\"metadata\":{},\"name\":\"PhoneNumber\",\"nullable\":true,\"type\":\"string\"},{\"metadata\":{},\"name\":\"FaxNumber\",\"nullable\":true,\"type\":\"string\"},{\"metadata\":{},\"name\":\"DeliveryRun\",\"nullable\":true,\"type\":\"double\"},{\"metadata\":{},\"name\":\"RunPosition\",\"nullable\":true,\"type\":\"double\"},{\"metadata\":{},\"name\":\"WebsiteURL\",\"nullable\":true,\"type\":\"string\"},{\"metadata\":{},\"name\":\"DeliveryAddressLine1\",\"nullable\":true,\"type\":\"string\"},{\"metadata\":{},\"name\":\"DeliveryAddressLine2\",\"nullable\":true,\"type\":\"string\"},{\"metadata\":{},\"name\":\"DeliveryPostalCode\",\"nullable\":true,\"type\":\"long\"},{\"metadata\":{},\"name\":\"DeliveryLocation\",\"nullable\":true,\"type\":\"string\"},{\"metadata\":{},\"name\":\"PostalAddressLine1\",\"nullable\":true,\"type\":\"string\"},{\"metadata\":{},\"name\":\"PostalAddressLine2\",\"nullable\":true,\"type\":\"string\"},{\"metadata\":{},\"name\":\"PostalPostalCode\",\"nullable\":true,\"type\":\"long\"},{\"metadata\":{},\"name\":\"LastEditedBy\",\"nullable\":true,\"type\":\"long\"},{\"metadata\":{},\"name\":\"ValidFrom\",\"nullable\":true,\"type\":\"timestamp\"},{\"metadata\":{},\"name\":\"ValidTo\",\"nullable\":true,\"type\":\"double\"}],\"type\":\"struct\"}}"},"clientVersion":"delta-rs.0.17.0"}}